mtnlog/._plot.py
mtnlog/__init__.py
mtnlog/json.py
mtnlog/performance.py
mtnlog/plot.py
mtnlog-1.2.17.dist-info/LICENSE.md
mtnlog-1.2.17.dist-info/METADATA
mtnlog-1.2.17.dist-info/WHEEL
mtnlog-1.2.17.dist-info/RECORD
