Metadata-Version: 2.1
Name: mtnlog
Version: 1.2.17
Summary: A simple performance logger for Python
Home-page: https://github.com/kentakoong/mtnlog
License: MIT
Keywords: performance,logging,python
Author: Wongkraiwich Chuenchomphu
Author-email: wongkraiwich@inedible.dev
Requires-Python: >=3.9
Classifier: License :: OSI Approved :: MIT License
Classifier: Operating System :: OS Independent
Classifier: Programming Language :: Python :: 3
Classifier: Programming Language :: Python :: 3.9
Classifier: Programming Language :: Python :: 3.10
Classifier: Programming Language :: Python :: 3.11
Classifier: Programming Language :: Python :: 3.12
Requires-Dist: matplotlib (>=3.9.2,<4.0.0)
Requires-Dist: nvitop (>=1.3.2,<2.0.0)
Requires-Dist: pandas (>=2.2.2,<3.0.0)
Requires-Dist: pandas-stubs (>=2.2.2.240807,<3.0.0.0)
Requires-Dist: psutil (>=6.0.0,<7.0.0)
Requires-Dist: tqdm (>=4.66.5,<5.0.0)
Project-URL: Documentation, https://github.com/kentakoong/mtnlog
Project-URL: Issues, https://github.com/kentakoong/mtnlog/issues
Project-URL: Repository, https://github.com/kentakoong/mtnlog
